roax/postgis.py
roax_postgis-1.0.0.dist-info/LICENSE
roax_postgis-1.0.0.dist-info/WHEEL
roax_postgis-1.0.0.dist-info/METADATA
roax_postgis-1.0.0.dist-info/RECORD
