Metadata-Version: 2.1
Name: roax-postgis
Version: 1.0.0
Summary: PostGIS extension for Roax.
Home-page: https://github.com/roax/roax-postgis/
License: MIT
Keywords: wsgi,framework,resource,openapi
Author: Paul Bryan
Author-email: pbryan@anode.ca
Requires-Python: >=3.6,<3.8
Classifier: Development Status :: 5 - Production/Stable
Classifier: Intended Audience :: Developers
Classifier: License :: OSI Approved :: MIT License
Classifier: Programming Language :: Python :: 3
Classifier: Programming Language :: Python :: 3.6
Classifier: Programming Language :: Python :: 3.7
Classifier: Topic :: Internet :: WWW/HTTP :: WSGI :: Application
Requires-Dist: roax-geo (>=1.1,<2.0)
Requires-Dist: roax-postgresql (>=1.1,<2.0)
